<?xml version="1.0" encoding="UTF-8"?><record_update table="sp_column">
  <sp_column action="INSERT_OR_UPDATE">
    <sys_id>681efe81efff4d779df9a4ad82b6029b</sys_id>
    <sys_scope display_value="x_2084960_commun_0">f1eeab0d83e94710c42256a6feaad344</sys_scope>
    <sys_update_name>sp_column_681efe81efff4d779df9a4ad82b6029b</sys_update_name>
    <class_name/>
    <order>1</order>
    <semantic_tag/>
    <size>12</size>
    <size_lg/>
    <size_sm>12</size_sm>
    <size_xs/>
    <sp_row>8c9bc197c9b94d8ab91673544464d73a</sp_row>
  </sp_column>
</record_update>
